tidevice3/__init__.py
tidevice3/__main__.py
tidevice3/api.py
tidevice3/cli/__init__.py
tidevice3/cli/app.py
tidevice3/cli/cli_common.py
tidevice3/cli/developer.py
tidevice3/cli/exec.py
tidevice3/cli/fsync.py
tidevice3/cli/info.py
tidevice3/cli/install.py
tidevice3/cli/list.py
tidevice3/cli/reboot.py
tidevice3/cli/relay.py
tidevice3/cli/runwda.py
tidevice3/cli/screenrecord.py
tidevice3/cli/screenshot.py
tidevice3/cli/tunneld.py
tidevice3/exceptions.py
tidevice3/utils/__init__.py
tidevice3/utils/common.py
tidevice3/utils/download.py
tidevice3-0.11.3.dist-info/LICENSE
tidevice3-0.11.3.dist-info/METADATA
tidevice3-0.11.3.dist-info/WHEEL
tidevice3-0.11.3.dist-info/entry_points.txt
tidevice3-0.11.3.dist-info/RECORD
