Metadata-Version: 2.1
Name: tidevice3
Version: 0.11.3
Summary: wrapper for pymobiledevice3 for easy use with iphone device
Home-page: https://github.com/codeskyblue/tidevice3
License: MIT
Author: codeskyblue
Author-email: codeskyblue@gmail.com
Requires-Python: >=3.8,<4.0
Classifier: License :: OSI Approved :: MIT License
Classifier: Programming Language :: Python :: 3
Classifier: Programming Language :: Python :: 3.8
Classifier: Programming Language :: Python :: 3.9
Classifier: Programming Language :: Python :: 3.10
Classifier: Programming Language :: Python :: 3.11
Classifier: Programming Language :: Python :: 3.12
Requires-Dist: click
Requires-Dist: fastapi
Requires-Dist: imageio[ffmpeg] (>=2.33.1,<3.0.0)
Requires-Dist: numpy
Requires-Dist: pillow (>=10.0,<11.0)
Requires-Dist: pydantic (>=2.5.3,<3.0.0)
Requires-Dist: pymobiledevice3 (>=4.2.3,<5.0.0)
Requires-Dist: requests
Requires-Dist: zeroconf (>=0.132.2,<0.133.0)
